plottings/__init__.py
plottings/base.py
plottings/file.py
plottings/value.py
plottings/views.py
django_plottings-0.0.3.dist-info/WHEEL
django_plottings-0.0.3.dist-info/METADATA
django_plottings-0.0.3.dist-info/RECORD
