Metadata-Version: 2.1
Name: django-plottings
Version: 0.0.3
Summary: A library to generate Matplotlib graphics within Django applications
Author-email: Jorge Monforte Gonzalez <yo@llou.net>
Classifier: Development Status :: 3 - Alpha
Classifier: Environment :: Web Environment
Classifier: License :: OSI Approved :: BSD License
Classifier: Programming Language :: Python
Classifier: Programming Language :: Python :: 3
Classifier: Programming Language :: Python :: 3.9
Classifier: Programming Language :: Python :: 3.10
Classifier: Programming Language :: Python :: 3.11
Classifier: Programming Language :: Python :: 3.12
Requires-Dist: django>=3.2.0
Requires-Dist: numpy>=1.26.0
Requires-Dist: matplotlib>=3.8.0
Project-URL: Documentation, https://django-plottings.readthedocs.io/en/latest/
Project-URL: Home, https://github.com/llou/django-plottings
